musrpy/__init__.py
musrpy/instruments.py
musrpy/models.py
musrpy-0.11.dist-info/LICENSE
musrpy-0.11.dist-info/METADATA
musrpy-0.11.dist-info/WHEEL
musrpy-0.11.dist-info/top_level.txt
musrpy-0.11.dist-info/RECORD
