Metadata-Version: 2.1
Name: musrpy
Version: 0.11
Summary: Analyse ROOT histograms from musrSimAna
Home-page: https://github.com/leo-collins/Pymusr
Author: Leo Collins
Author-email: leocollins511@gmail.com
Classifier: Programming Language :: Python :: 3
Classifier: License :: OSI Approved :: GNU General Public License v3 or later (GPLv3+)
Classifier: Operating System :: OS Independent
Requires-Python: >=3.10
License-File: LICENSE
